MANIFEST.in
README.rst
setup.py
recoder/__init__.py
recoder/__main__.py
recoder/base_recoder.py
recoder/pyver.py
recoder/tests.py
recoder.egg-info/PKG-INFO
recoder.egg-info/SOURCES.txt
recoder.egg-info/dependency_links.txt
recoder.egg-info/not-zip-safe
recoder.egg-info/top_level.txt
recoder/builder/__init__.py
recoder/builder/__main__.py
recoder/builder/builder.py
recoder/cyrillic/3grams.json
recoder/cyrillic/__init__.py
recoder/cyrillic/plus_words.json
recoder/cyrillic/recoder.py