Metadata-Version: 1.1
Name: recoder
Version: 0.3.1
Summary: Tool (and lib) for coding fix.
Home-page: https://bitbucket.org/dkuryakin/recoder
Author: David Kuryakin
Author-email: dkuryakin@gmail.com
License: mit
Download-URL: https://bitbucket.org/dkuryakin/recoder/get/master.tar.gz
Keywords: cyrillic,encoding,coding,fix,decoder,recoder,i18n
Platform: any
Classifier: Development Status :: 4 - Beta
Classifier: Environment :: Web Environment
Classifier: Intended Audience :: Developers
Classifier: License :: OSI Approved :: MIT License
Classifier: Operating System :: OS Independent
Classifier: Programming Language :: Python
Classifier: Topic :: Internet :: WWW/HTTP
Classifier: Topic :: Text Processing :: Linguistic
Classifier: Topic :: Software Development :: Libraries :: Python Modules
